pygvas/__init__.py
pygvas/detect_gvas_format.py
pygvas/engine_tools.py
pygvas/error.py
pygvas/gvas2json.py
pygvas/gvas_file.py
pygvas/gvas_types.py
pygvas/gvas_utils.py
pygvas/json2gvas.py
pygvas/properties/__init__.py
pygvas/properties/aggregator_properties.py
pygvas/properties/delegate_property.py
pygvas/properties/enum_property.py
pygvas/properties/field_path_property.py
pygvas/properties/name_property.py
pygvas/properties/numerical_properties.py
pygvas/properties/object_property.py
pygvas/properties/property_base.py
pygvas/properties/standard_structs.py
pygvas/properties/str_property.py
pygvas/properties/text_property.py
pygvas-0.9.6.data/data/HOWTO.md
pygvas-0.9.6.data/data/do_unit_tests.bat
pygvas-0.9.6.data/data/do_unit_tests.py
pygvas-0.9.6.data/data/do_utility_tests.bat
pygvas-0.9.6.data/data/do_utility_tests.py
pygvas-0.9.6.dist-info/licenses/LICENSE
pygvas-0.9.6.dist-info/METADATA
pygvas-0.9.6.dist-info/WHEEL
pygvas-0.9.6.dist-info/entry_points.txt
pygvas-0.9.6.dist-info/top_level.txt
pygvas-0.9.6.dist-info/RECORD
