Metadata-Version: 2.4
Name: pygvas
Version: 0.9.6
Summary: GVAS<->JSON De/Serializer in Python
Author-email: Robin Fredericksen <refredericksen@gmail.com>
License-Expression: CC-BY-NC-SA-4.0
Project-URL: Homepage, https://github.com/Ryzhara/pygvas
Project-URL: Repository, https://github.com/Ryzhara/pygvas.git
Project-URL: Overview, https://github.com/Ryzhara/pygvas/blob/main/docs/gvas_overview.md
Project-URL: Tracker, https://github.com/Ryzhara/pygvas/issues
Keywords: ue4,ue5,pygvas,gvas,json,sav
Classifier: Development Status :: 4 - Beta
Classifier: Programming Language :: Python
Requires-Python: >=3.9
License-File: LICENSE
Requires-Dist: pydantic>=2.11.3
Dynamic: license-file
